refinegems/__init__.py
refinegems/analysis_biocyc.py
refinegems/analysis_db.py
refinegems/analysis_kegg.py
refinegems/biomass.py
refinegems/charges.py
refinegems/comparison.py
refinegems/curate.py
refinegems/cvterms.py
refinegems/databases.py
refinegems/entities.py
refinegems/gapfill.py
refinegems/growth.py
refinegems/investigate.py
refinegems/io.py
refinegems/modelseed.py
refinegems/pathways.py
refinegems/polish.py
refinegems/sboann.py
refinegems/util.py
refinegems/data/__init__.py
refinegems/data/database/__init__.py
refinegems/data/database/current_bigg_db_version.txt
refinegems/data/database/data.db
refinegems/data/database/sbo_media_db.sql
refinegems/example/__init__.py
refinegems/example/example_inputs/__init__.py
refinegems/example/example_inputs/manual_curation.xlsx
refinegems/example/example_inputs/media_db.csv
refinegems/example/example_inputs/modelName_gapfill_analysis_date_example.xlsx
refineGEMs-1.5.0.dist-info/LICENSE
refineGEMs-1.5.0.dist-info/METADATA
refineGEMs-1.5.0.dist-info/WHEEL
refineGEMs-1.5.0.dist-info/top_level.txt
refineGEMs-1.5.0.dist-info/RECORD
