Metadata-Version: 2.1
Name: refineGEMs
Version: 1.5.0
Summary: refineGEMs: a python package intended to help with the curation of genome-scale metabolic models (GEMS)
Author: Gwendolyn O. Döbel
Author-email: Famke Baeuerle <famke.baeuerle@gmail.com>
Maintainer: Tobias Fehrenbach, Carolin Brune
License: MIT
Project-URL: homepage, https://github.com/draeger-lab/refinegems
Project-URL: documentation, https://refinegems.readthedocs.io/en/latest/
Keywords: Systems Biology,GEM,Metabolic Modelling,Python Package
Classifier: Topic :: Scientific/Engineering :: Bio-Informatics
Classifier: Programming Language :: Python
Classifier: Programming Language :: SQL
Classifier: License :: OSI Approved :: MIT License
Requires-Python: <3.11,>=3.9
License-File: LICENSE
Requires-Dist: cobra <0.28.0,>=0.26.0
Requires-Dist: biopython >=1.79
Requires-Dist: bioregistry
Requires-Dist: bioservices
Requires-Dist: Deprecated
Requires-Dist: importlib-resources <=5.13.0
Requires-Dist: memote <2.0.0,>=0.13.0
Requires-Dist: pandas >=1.2.4
Requires-Dist: numpy <2.0.0,>=1.20.3
Requires-Dist: gffutils >=0.10.1
Requires-Dist: markupsafe >=2.0.1
Requires-Dist: depinfo >=1.7.0
Requires-Dist: sortedcontainers >=2.4.0
Requires-Dist: libchebipy >=1.0.10
Requires-Dist: ratelimit >=2.2.1
Requires-Dist: sqlalchemy >=2.0.0
Requires-Dist: venn >=0.1.3
Requires-Dist: ols-client >=0.1.3
Requires-Dist: seaborn >=0.12.2
Requires-Dist: click >=8.1.3
